{
  "members": {
    "mentors": [
      {
        "id": "mentor-13",
        "name": {
          "en": "13",
          "zh-TW": "13"
        },
        "image_link": "https://raw.githubusercontent.com/Galile-Vincent/SCTC_Sources/main/img/13.jpeg",
        "intro": {
          "en": "Senior iOS Developer",
          "zh-TW": "資深 iOS 工程師、13 報主編"
        },
        "twitter": "https://x.com/ethanhuang13",
        "threads": "https://threads.net/@ethanhuang13",
        "yt": "https://www.youtube.com/@ethanhuang13"
      },
      {
        "id": "mentor-jane",
        "name": {
          "en": "Jane",
          "zh-TW": "Jane"
        },
        "image_link": "https://raw.githubusercontent.com/Galile-Vincent/SCTC_Sources/main/img/jane.png",
        "intro": {
          "en": "iOS & AI Developer Community & Content Creator Leader",
          "zh-TW": "iOS & AI 開發者社群、內容創作者領導者"
        },
        "x": "https://x.com/janechao_dev",
        "yt": "https://www.youtube.com/@ChaoCode"
      },
      {
        "id": "mentor-kai",
        "name": {
          "en": "Kai",
          "zh-TW": "Kai"
        },
        "image_link": "https://images.imagerenderer.com/images-medium-large-5/neon-blue-question-mark-ikon-ikon-images.jpg",
        "intro": {
          "en": "Foreign Tech Company Market Strategy Manager",
          "zh-TW": "外商科技公司市場策略經理"
        }
      }
    ],
    "members": [
      {
        "id": "member-vincent",
        "name": {
          "en": "Vincent",
          "zh-TW": "Vincent"
        },
        "image_link": "https://raw.githubusercontent.com/Galile-Vincent/SCTC_Sources/main/img/vincent.jpg",
        "intro": {
          "en": "WWDC SSC Winner '24 '25, MAIC First Place '25",
          "zh-TW": "WWDC SSC 2024、2025 學生得獎者, 2025 MAIC 一等獎"
        },
        "linkedin": "https://www.linkedin.com/in/hung-yeh-chiang",
        "threads": "https://threads.net/@vincent._0523"
      }
    ]
  }
}
